libucx/GIT_COMMIT
libucx/VERSION
libucx/__init__.py
libucx/_version.py
libucx/load.py
libucx/bin/io_demo
libucx/bin/ucx_info
libucx/bin/ucx_perftest
libucx/bin/ucx_perftest_daemon
libucx/bin/ucx_read_profile
libucx/etc/ucx/ucx.conf
libucx/include/ucm/api/ucm.h
libucx/include/ucp/api/ucp.h
libucx/include/ucp/api/ucp_compat.h
libucx/include/ucp/api/ucp_def.h
libucx/include/ucp/api/ucp_version.h
libucx/include/ucs/algorithm/crc.h
libucx/include/ucs/algorithm/qsort_r.h
libucx/include/ucs/algorithm/string_distance.h
libucx/include/ucs/arch/atomic.h
libucx/include/ucs/arch/bitops.h
libucx/include/ucs/arch/global_opts.h
libucx/include/ucs/arch/aarch64/bitops.h
libucx/include/ucs/arch/aarch64/global_opts.h
libucx/include/ucs/arch/generic/atomic.h
libucx/include/ucs/arch/ppc64/bitops.h
libucx/include/ucs/arch/ppc64/global_opts.h
libucx/include/ucs/arch/rv64/bitops.h
libucx/include/ucs/arch/rv64/global_opts.h
libucx/include/ucs/arch/x86_64/atomic.h
libucx/include/ucs/arch/x86_64/bitops.h
libucx/include/ucs/arch/x86_64/global_opts.h
libucx/include/ucs/async/async_fwd.h
libucx/include/ucs/config/global_opts.h
libucx/include/ucs/config/ini.h
libucx/include/ucs/config/parser.h
libucx/include/ucs/config/types.h
libucx/include/ucs/datastruct/array.h
libucx/include/ucs/datastruct/callbackq.h
libucx/include/ucs/datastruct/callbackq_compat.h
libucx/include/ucs/datastruct/hlist.h
libucx/include/ucs/datastruct/khash.h
libucx/include/ucs/datastruct/linear_func.h
libucx/include/ucs/datastruct/list.h
libucx/include/ucs/datastruct/mpool.h
libucx/include/ucs/datastruct/mpool_set.h
libucx/include/ucs/datastruct/pgtable.h
libucx/include/ucs/datastruct/piecewise_func.h
libucx/include/ucs/datastruct/queue_types.h
libucx/include/ucs/datastruct/strided_alloc.h
libucx/include/ucs/datastruct/string_buffer.h
libucx/include/ucs/datastruct/string_set.h
libucx/include/ucs/debug/debug.h
libucx/include/ucs/debug/log_def.h
libucx_cu12-1.19.0.dist-info/METADATA
libucx_cu12-1.19.0.dist-info/WHEEL
libucx_cu12-1.19.0.dist-info/entry_points.txt
libucx_cu12-1.19.0.dist-info/top_level.txt
libucx_cu12-1.19.0.dist-info/RECORD
libucx_cu12-1.19.0.dist-info/licenses/LICENSE
